plain_db/__init__.py
plain_db-0.0.46.dist-info/LICENSE
plain_db-0.0.46.dist-info/METADATA
plain_db-0.0.46.dist-info/WHEEL
plain_db-0.0.46.dist-info/top_level.txt
plain_db-0.0.46.dist-info/RECORD
