Metadata-Version: 2.1
Name: plain-db
Version: 0.0.46
Summary: Plain txt DB
Home-page: https://github.com/gaoyunzhi/plain_db
Author: Yunzhi Gao
Author-email: gaoyunzhi@gmail.com
License: UNKNOWN
Platform: UNKNOWN
Classifier: Programming Language :: Python :: 3
Classifier: License :: OSI Approved :: MIT License
Classifier: Operating System :: OS Independent
Requires-Python: >=3.0
License-File: LICENSE
